clideq/__init__.py
clideq/cli.py
clideq-0.1.1.dist-info/METADATA
clideq-0.1.1.dist-info/WHEEL
clideq-0.1.1.dist-info/entry_points.txt
clideq-0.1.1.dist-info/RECORD
