Metadata-Version: 2.3
Name: clideq
Version: 0.1.1
Summary: clideq CLI
License: Proprietary
Author: clideq@boltu.ai
Requires-Python: >=3.11,<4.0
Classifier: License :: Other/Proprietary License
Classifier: Programming Language :: Python :: 3
Classifier: Programming Language :: Python :: 3.11
Classifier: Programming Language :: Python :: 3.12
Classifier: Programming Language :: Python :: 3.13
